aiomailru/__init__.py
aiomailru/api.py
aiomailru/browser.py
aiomailru/exceptions.py
aiomailru/parsers.py
aiomailru/scrapers.py
aiomailru/sessions.py
aiomailru/utils.py
aiomailru/objects/__init__.py
aiomailru/objects/event.py
aiomailru/objects/group.py
tests/__init__.py
tests/conftest.py
tests/test_scrapers.py
tests/test_sessions.py
aiomailru-0.1.1.post1.dist-info/LICENSE
aiomailru-0.1.1.post1.dist-info/METADATA
aiomailru-0.1.1.post1.dist-info/WHEEL
aiomailru-0.1.1.post1.dist-info/top_level.txt
aiomailru-0.1.1.post1.dist-info/RECORD
