Metadata-Version: 2.1
Name: aiomailru
Version: 0.1.1.post1
Summary: Python Mail.Ru API wrapper
Home-page: https://github.com/KonstantinTogoi/aiomailru
Author: Konstantin Togoi
Author-email: konstantin.togoi@protonmail.com
License: BSD
Download-URL: https://pypi.org/project/aiomailru/
Project-URL: Documentation, https://aiomailru.readthedocs.io
Keywords: mail.ru rest api scrapers asyncio
Platform: Any
Classifier: Development Status :: 5 - Production/Stable
Classifier: Environment :: Web Environment
Classifier: Framework :: AsyncIO
Classifier: Intended Audience :: Developers
Classifier: License :: OSI Approved :: BSD License
Classifier: Operating System :: OS Independent
Classifier: Programming Language :: Python
Classifier: Programming Language :: Python :: 3.5
Classifier: Programming Language :: Python :: 3.6
Classifier: Programming Language :: Python :: 3.7
Classifier: Programming Language :: Python :: 3.8
Classifier: Programming Language :: Python :: 3 :: Only
Classifier: Topic :: Internet
Classifier: Topic :: Internet :: WWW/HTTP
Classifier: Topic :: Software Development :: Libraries :: Python Modules
Requires-Python: >=3.5
Requires-Dist: aiohttp (>=3.0.0)
Requires-Dist: yarl
Provides-Extra: scrapers
Requires-Dist: pyppeteer (<=0.0.25) ; extra == 'scrapers'
